Workbook

Sheet Investimentos Fixos
A1: Investimentos Fixos (Criacao, hospedagem e venda em site de jogo virtual)
B3: 1- Máquinas e Equipamentos | G3: 3- Móveis e Utensílios
B4: Descrição | C4: Qtde | D4: Valor Unit. | E4: Total | G4: Descrição | H4: Qtde | J4: Total
B5: Mesa digitalizadora | C5: 1 | D5: 1499.44 | E5: =C5*D5 -> 1499.44 | J5: =H5*I5 -> 0
J6: =H6*I6 -> 0
B7: Devkits Nintendo Switch | C7: 1 | D7: 2477.79 | E7: =C7*D7 -> 2477.79 | J7: =H7*I7 -> 0
B8: Servidor Rack PowerEdge R260 | C8: 1 | D8: 6000 | E8: =C8*D8 -> 6000 | J8: =H8*I8 -> 0
B9: Softwares com licença perpétua | C9: 1 | D9: 5000 | E9: =C9*D9 -> 5000
G11: Total | J11: =SUM(J5:J10) -> 0
B12: Total | E12: =SUM(E5:E11) -> 14977.23
G13: 3- Veículos
B14: Mesa digitalizadora para finalização das artes, Devkits do nintendo switch para aplicação do jogo na plataforma da nintendo, um servidor local para armazenamento do jogo para evitar problemas de licensa e Licença de softwares variados como Photoshop e editores de video para criação de trailer etc | G14: Descrição | H14: Qtde | I14: Valor Unit. | J14: Total
G16: Total | J16: =SUM(J15) -> 0
G19: TOTAL DE INVESTIMENTOS FIXOS | J19: =E12+J11+J16+E19 -> 14977.23 | L19: FONTES: | M19: mesa digitalizadora: https://shopee.com.br/product/711046067/23493921788?gads_t_sig=VTJGc2RHVmtYMTlxTFVSVVRrdENkVHQ3ZkZSUTMrR3pBWmZZNzdrcnRBMDloYXZ0cG5TQ0d1ak02bU42bVdRalNnMEJzVWRqeTRyWHg5Q3pNNTg4Mnd4ZEpHcnlvZjFZalJzcjRmTW5VOVp3YXhpMHRkbVF2K056clJGakxVdGlKNmZpUFVkTDV3NlkxOUlSSEpQQWZBPT0 Devkit nintendo: https://xsolla.com/blog/score-dev-kits-for-xbox-playstation-and-nintendo
M27: Servidor: https://www.dell.com/pt-br/shop/cty/pdp/spd/poweredge-r260/pe_r260_18399_bcc_1?tfcid=31768715&gacd=9687031-14067-5761040-273175705-0&dgc=ST&sa360CID=71700000122700339&gclsrc=aw.ds&&gad_source=1&gad_campaignid=22726520047&gclid=Cj0KCQjwwZDFBhCpARIsAB95qO3GfR84tpRPaPzqS0jQOibWHJBEzSL2DRUm2zaPI8IwieHz3FrRPhAaAtPTEALw_wcB

Sheet Capital de Giro
A1: 5- Capital de Giro (suficiente para 6 meses)
A2: Descrição | B2: Valor mensal | C2: Tempo (mês) | D2: Total R$
A3: Planilha 10 - Apuração do custo de Matéria-Prima e Mercadorias Vendidas | B3: 0 | C3: 6 | D3: =B3*C3 -> 0
A4: Planilha 11 - Estimativa dos custos de comercialização | B4: =FaturamentoXCustos!D35 -> 59118.4 | C4: 6 | D4: =B4*C4 -> 354710.4
A5: Planilha 14 - Estimativa de custos fixos operacionais mensais(50%) | B5: =('cont... custos'!B41) -> 16.33 | C5: 6 | D5: =B5*C5 -> 97.98
A6: Total | D6: =SUM(D4:D5) -> 354808.38

Sheet Investimentos Pré-Operacionais
A1: Criacao, hospedagem e venda em site de jogo virtual
A2: 6- Investimentos Pré-Operacionais
A3: Descrição | B3: R$
A4: Licensas para publicação em plataformas | B4: 1345.66 | C4: Numero total de impressões considerando o custo de 4,29 por mil impressões dá um total de 11.655.011.
A5: Marketing Digital | B5: 50000
A8: Total | B8: =SUM(B4:B7) -> 51345.66
A10: Total de Investimentos Pré Operacionais | B10: =B8+F6 -> 51345.66
A12: FONTES: | B12: Licensas para publicação em plataformas:
B13: https://store.steampowered.com/sub/163632/?l=portuguese
B14: https://gdevelop.io/page/how-to-publish-game-on-epic-games-store-and-why-you-should
B15: https://gamemaker.io/pt-BR/get
B16: https://gamemaker.io/pt-BR/get
B17: https://froggyads.com/blog/average-cpm-for-online-advertising/?utm_source=chatgpt.com#average_cpm_for_online_advertising

Sheet Investimento Total
A1: 7 - Investimento Total
A2: Descrição dos Investimentos | B2: Valor | C2: Percentual
A3: Investimentos Fixos | B3: ='Investimentos Fixos'!J19 -> 14977.23 | C3: =B3/B6 -> 0.035564279
A4: Capital de Giro(6 meses) | B4: ='Capital de Giro'!D6 -> 354808.38 | C4: =B4/B6 -> 0.84251255
A5: Investimentos Pré-Operacionais | B5: ='Investimentos Pré-Operacionais'!B10 -> 51345.66 | C5: =B5/B6 -> 0.12192317
A6: Total | B6: =SUM(B3:B5) -> 421131.27

Sheet FaturamentoXCustos
A1: 8- Estimativa de Faturamento Mensal
A2: Produto/Serviço | B2: Qtde (estimativa de vendas) | C2: Preço Unitário da Venda | D2: Faturamento Total
A3: Downloads Aplicativo | B3: 4315 | C3: 30 | D3: =C3*B3 -> 129450 | F3: Calculo de vendas dos anuncios: (considere CTR de 1,815% e taxa de conversão de 1%) | G3: 2115
A4: OST para uso externo | B4: 431 | C4: 10 | D4: =B4*C4 -> 4310 | F4: Vendas naturais da steam, por mês: | G4: 600
D5: =B5*C5 -> 0 | F5: Nintendo (considerando que esse genero de jogo é conhecido pelas vendas nessa plataforma | G5: 700
D6: =B6*C6 -> 0
D7: =B7*C7 -> 0 | F7: PlayStation Store | G7: 400
D8: =B8*C8 -> 0 | F8: Xbox Store | G8: 400
D9: =B9*C9 -> 0 | F9: Epic | G9: 100
A10: Total | D10: =SUM(D3:D4) -> 133760
A12: 9- Estimativa dos Custos Variáveis | F12: OST (considerando uma taxa baixa de 1%)
A13: Matéria-Prima | B13: Quant | C13: Preço | D13: Preço Total
D14: 0
D15: 0
D16: =B16*C16 -> 0
D17: =C17 -> 0
A18: Total | D18: =SUM(D14:D19) -> #REF!
A20: 10 - Apuração do custo de Matéria-Prima e Mercadorias Vendidas
A21: Produto/Serviço | B21: Estimativa de vendas | C21: Custo Unit de Mat. Prima | D21: Custo Mensal de Mat. Prima
D27: =B27*C27 -> 0
A28: Total | D28: =SUM(D22:D27) -> 0
A30: 11 - Estimativa dos custos de comercialização
A31: Descrição | B31: % | C31: Faturamento Estimado | D31: Custo Total
A32: Taxa para manter nas plataformas (steam, xbox, playstation e nintendo) | B32: 0.3 | C32: =(D10) -> 133760 | D32: =(B32*C32)-9900 -> 30228
A33: Imposto para pessoa fisica | B33: 0.275 | C33: =(D10) -> 133760 | D33: =(B33*C33)-9900 -> 26884
A34: Cartão Crédito | B34: 0.05 | C34: =D10*0.3 -> 40128 | D34: =C34*B34 -> 2006.4
D35: =SUM(D32:D34) -> 59118.4
D37: Fontes: | F37: https://v4company.com/marketing-digital/ctr
F38: https://vwo.com/blog/conversion-rate-and-click-through-rate-difference
F39: https://splicedonline.com/how-many-copies-does-the-average-game-on-steam-sell/

Sheet cont... custos
A1: 12 - Estimativa dos custos com Mão-de-Obra
A2: Função | B2: No de Empregados | C2: Salário Mensal | D2: Subtotal | E2: % de Encargos Sociais | F2: Encargos Sociais | G2: Benefícios | H2: Total
D3: =B3*C3 -> 0 | F3: =D3*E3 -> 0 | H3: =(D3+F3)+(G3*B3) -> 0
D4: =B4*C4 -> 0 | F4: =D4*E4 -> 0 | H4: =(D4+F4)+(G4*B4) -> 0
A5: Total de custos com mão de Obra (mensal) - Levando em consideração o Simples Nacional | H5: =SUM(H3:H4) -> 0
A7: 13 - Estimativa de custo com Depreciação
A8: Ativos Fixos | B8: Quant. | C8: Valor do Bem | D8: Total em Bens | E8: Vida útil em anos | F8: Depreciação Anual | G8: Depreciação Mensal
A9: ='Investimentos Fixos'!B5 -> Mesa digitalizadora | B9: ='Investimentos Fixos'!C5 -> 1 | C9: ='Investimentos Fixos'!D5 -> 1499.44 | D9: =B9*C9 -> 1499.44 | G9: =F9/12 -> 0
A10: ='Investimentos Fixos'!B6 -> 0 | B10: ='Investimentos Fixos'!C6 -> 0 | C10: ='Investimentos Fixos'!D6 -> 0 | D10: =B10*C10 -> 0
A11: ='Investimentos Fixos'!B7 -> Devkits Nintendo Switch | B11: ='Investimentos Fixos'!C7 -> 1 | C11: ='Investimentos Fixos'!D7 -> 2477.79 | D11: =B11*C11 -> 2477.79
A12: ='Investimentos Fixos'!B8 -> Servidor Rack PowerEdge R260 | B12: ='Investimentos Fixos'!C8 -> 1 | C12: ='Investimentos Fixos'!D8 -> 6000 | D12: =B12*C12 -> 6000 | G12: =F12/12 -> 0
A13: ='Investimentos Fixos'!B9 -> Softwares com licença perpétua | B13: ='Investimentos Fixos'!C9 -> 1 | C13: ='Investimentos Fixos'!D9 -> 5000 | D13: =B13*C13 -> 5000
A20: Total de custos com depreciação (mensal) | G20: =SUM(G9:G19) -> 0
A23: 14 - Estimativa de custos fixos operacionais mensais | D23: Custos mensais
A24: Descrição | B24: Custo Total Mensal | D24: Variáveis | E24: =FaturamentoXCustos!$D$35 -> 59118.4
A25: Depreciação | B25: =G20 -> 0 | D25: Fixos | E25: =B41 -> 16.33
A26: Custo dominio e deixar o site online | B26: 16.33
A41: Total | B41: =SUM(B25:B40) -> 16.33
A44: A taxa de depreciação é dada como 0 pois nenhum dos itens comprados, se quebrarem no futuro não interferem no lucro do jogo, que já estará em venda
A52: Fontes: | B52: https://registro.br/dominio
B53: https://www.hostinger.com/br/hospedagem-de-sites?utm_campaign=Generic-Hosting|NT:Se|LO:BR&utm_medium=ppc&gad_source=1&gad_campaignid=19605518140&gclid=Cj0KCQjwwZDFBhCpARIsAB95qO2nfRgWLPHbGX3pD44ehZ9RmgdaOS63HiASc7a3R40SOwphFu7JnXcaAqKmEALw_wcB#pricing

Sheet Resultado Final
A1: Demonstrativo de Resultados
A2: Planilhas | B2: Descrição | C2: R$ | D2: % | F2: Faturamento mensal | G2: =C3 -> 133760
A3: Planilha 8 | B3: 1. Estimativa de Faturamento Mensal | C3: =FaturamentoXCustos!D10 -> 133760 | F3: Lucratividade | G3: =D10 -> 0.55790423 | H3: =C10 -> 74625.27
B4: 2. Custos Variáveis Totais | C4: =FaturamentoXCustos!D28 -> 0 | F4: Rentabilidade | G4: =B32 -> 0.17720192 | H4: Devolve esse percentual do capital Investido ao mês
A5: Planilha 10 | B5: Apuração do custo de Matéria-Prima e Mercadorias Vendidas | F5: Retorno do Investimento (Em meses) | G5: =B38 -> 5.6432797 | H5: meses
A6: Planilha 11 | B6: Estimativas de custo de Comercialização (impostos, cartão crédito, etc) | C6: =FaturamentoXCustos!D35 -> 59118.4
B7: Subtotal | C7: =SUM(C4:C6) -> 59118.4
B8: 3. Margem de Contribuição (1-2) | C8: =C3-C7 -> 74641.6
A9: Planilha 14 | B9: 4. Custos Fixos Totais | C9: ='cont... custos'!B41 -> 16.33
B10: 5. Resultado Operacional (Lucro ou Prejuizo) (3-4) | C10: =C8-C9 -> 74625.27 | D10: =C10/C3 -> 0.55790423
A13: Ponto de Equilibrio
A14: Ponto de Equilibrio = Custo Fixo total / Indice da margem de Contribuição
A15: Indice da margem de Contribuição = Magem de Contribuição / Receita (estimativa de faturamento)
A16: APLICAÇÃO DAS FÓRMULAS ACIMA E RESULTADO DO PONTO DE EQUILIBRIO (PE)
A17: Indice da Margem de Contribuição | B17: =C8/C3 -> 0.55802632
A18: Ponto de Equilíbrio | B18: =C9/B17 -> 29.263853
A19: Isso quer dizer que quando a Autollar chegar ao faturamento de informado no Ponto de Equilibrio, estará cobrindo todos os custos da empresa e daí por diante não terá mais Prejuizo, somente Lucro.
A22: Lucratividade
A23: Lucratividade = Lucro Líquido/Receita Total x 100
A24: APLICAÇÃO DAS FÓRMULAS ACIMA E RESULTADO DO PERCENTUAL DE LUCRATIVIDADE
A25: Lucratividade | B25: =C10/C3 -> 0.55790423
A26: Isso quer dizer que o Projeti tem a Lucratividade informada acima!
A29: Rentabilidade
A30: Rentabilidade = Lucro Líquido/Investimento Total (para chegar ao percentual multiplica o result. por 100)
A31: APLICAÇÃO DA FÓRMULA ACIMA E RESULTADO DO PERCENTUAL DE LUCRATIVIDADE
A32: Rentabilidade | B32: =C10/'Investimento Total'!B6 -> 0.17720192
A33: Isso quer dizer que a cada mês, os empresários recupera o perentual acima em relação ao valor investido através dos lucros obtidos no negócio!
A35: Prazo de Retorno do Investimento
A36: Prazo do Retorno no Investimento = Investimento Total / Lucro Liquido
A37: APLICAÇÃO DA FÓRMULA ACIMA E RESULTADO DO PERCENTUAL DE LUCRATIVIDADE
A38: Prazo de Retorno do Investimento | B38: ='Investimento Total'!B6/C10 -> 5.6432797
A39: Isso quer dizer que após 2 meses no inicio de atividade da empresa, os empreededores terá recuperado, sob a forma de lucro, tudo o que gastou com a montagem da empresa!
